{
  "request_count": 220,
  "p50_latency_us": 393714,
  "p95_latency_us": 743315,
  "p99_latency_us": 771767,
  "p95_queue_share_permille": 980,
  "p95_service_share_permille": 392,
  "inflight_trend": {
    "gauge": "mixed_contention_inflight",
    "sample_count": 440,
    "peak_count": 201,
    "p95_count": 191,
    "growth_delta": -1,
    "growth_per_sec_milli": -1156
  },
  "warnings": [],
  "primary_suspect": {
    "kind": "application_queue_saturation",
    "score": 95,
    "confidence": "high",
    "evidence": [
      "Queue wait at p95 consumes 98.0% of request time.",
      "Observed queue depth sample up to 196."
    ],
    "next_checks": [
      "Inspect queue admission limits and producer burst patterns.",
      "Compare queue wait distribution before and after increasing worker parallelism."
    ]
  },
  "secondary_suspects": [
    {
      "kind": "downstream_stage_dominates",
      "score": 35,
      "confidence": "low",
      "evidence": [
        "Stage 'downstream_call' has p95 latency 32407 us across 220 samples.",
        "Stage 'downstream_call' cumulative latency is 3782929 us (43 permille of request latency).",
        "Stage 'downstream_call' contributes 25 permille of tail request latency."
      ],
      "next_checks": [
        "Inspect downstream dependency behind stage 'downstream_call'.",
        "Collect downstream service timings and retry behavior during tail windows.",
        "Review downstream SLO/error budget and align retry budget/backoff with it."
      ]
    }
  ]
}
